{
  "generated_at": "2026-04-16",
  "month": "April 2026",
  "trending_topics": [
    {
      "topic": "Autumn selling season momentum",
      "relevance": "high",
      "content_angle": "Why autumn is a smart time to list in East Auckland"
    },
    {
      "topic": "OCR and mortgage rate watch",
      "relevance": "high",
      "content_angle": "What current rates mean for East Auckland buyers now"
    },
    {
      "topic": "Smart home features boosting sale prices",
      "relevance": "high",
      "content_angle": "Tech upgrades that impress buyers at open homes"
    },
    {
      "topic": "Multigenerational living demand rising",
      "relevance": "medium",
      "content_angle": "East Auckland homes perfect for extended families"
    },
    {
      "topic": "Eco-friendly home upgrades",
      "relevance": "medium",
      "content_angle": "Energy-efficient features buyers are actively seeking"
    },
    {
      "topic": "First-home buyer confidence returning",
      "relevance": "high",
      "content_angle": "Steps first-home buyers should take right now"
    },
    {
      "topic": "Investor confidence lifting in NZ",
      "relevance": "medium",
      "content_angle": "Why East Auckland remains a strong investment area"
    }
  ],
  "trending_hashtags": [
    "#JinnyLeeRealEstate",
    "#EastAucklandRealEstate",
    "#AucklandProperty",
    "#SmarterSelling",
    "#BetterBuying",
    "#RayWhiteBotany",
    "#EastAuckland",
    "#AucklandHomes",
    "#NZRealEstate",
    "#HomeSellingTips",
    "#FirstHomeBuyer",
    "#AucklandLiving",
    "#PropertyNZ",
    "#OpenHome",
    "#NZProperty",
    "#HomeBuyingNZ",
    "#RealEstateNZ",
    "#EastAucklandLife"
  ],
  "seasonal_context": "Autumn 2026 brings motivated sellers and serious buyers, ideal for East Auckland listings.",
  "content_opportunities": [
    {
      "angle": "5 reasons autumn is great for selling your East Auckland home",
      "why": "Seasonal urgency drives engagement from homeowners considering listing",
      "format": "image"
    },
    {
      "angle": "What the latest OCR means for your buying power",
      "why": "Rate decisions are top of mind for buyers and sellers this month",
      "format": "text"
    },
    {
      "angle": "Smart home features buyers love in East Auckland right now",
      "why": "Tech-integrated design is trending strongly among 2026 buyers",
      "format": "image"
    },
    {
      "angle": "First-home buyer checklist for East Auckland in April 2026",
      "why": "Entry-level buyers are re-entering the market with growing confidence",
      "format": "image"
    },
    {
      "angle": "Behind the sold sign: a recent East Auckland success story",
      "why": "Social proof builds trust and drives seller enquiries",
      "format": "image"
    },
    {
      "angle": "Your suburb spotlight: what's selling in East Auckland this autumn",
      "why": "Hyper-local content performs well and positions Jinny as area expert",
      "format": "image"
    }
  ],
  "avoid_this_week": [
    "Generic national property statistics without local context",
    "Overly polished corporate content lacking personality",
    "Repetitive listing posts without storytelling or results"
  ],
  "recommended_hook_styles": [
    "Thinking of selling this autumn? Here's what you need to know first.",
    "Most East Auckland buyers don't realise this about the current market.",
    "3 things smart sellers do before listing their home this April.",
    "If you're a first-home buyer, this one is for you."
  ],
  "news_summary": "Investor confidence is lifting across New Zealand in 2026, with moderating supply and returning rental growth signalling opportunity in East Auckland."
}